llm_gemini.py
llm_gemini-0.28.1.dist-info/licenses/LICENSE
llm_gemini-0.28.1.dist-info/METADATA
llm_gemini-0.28.1.dist-info/WHEEL
llm_gemini-0.28.1.dist-info/entry_points.txt
llm_gemini-0.28.1.dist-info/top_level.txt
llm_gemini-0.28.1.dist-info/RECORD
