Metadata-Version: 2.4
Name: llm-gemini
Version: 0.28.1
Summary: LLM plugin to access Google's Gemini family of models
Author: Simon Willison
License-Expression: Apache-2.0
Project-URL: Homepage, https://github.com/simonw/llm-gemini
Project-URL: Changelog, https://github.com/simonw/llm-gemini/releases
Project-URL: Issues, https://github.com/simonw/llm-gemini/issues
Project-URL: CI, https://github.com/simonw/llm-gemini/actions
Requires-Python: >=3.10
License-File: LICENSE
Requires-Dist: llm>=0.27
Requires-Dist: httpx
Requires-Dist: ijson
Provides-Extra: test
Requires-Dist: pytest; extra == "test"
Requires-Dist: pytest-recording; extra == "test"
Requires-Dist: pytest-asyncio; extra == "test"
Requires-Dist: cogapp; extra == "test"
Dynamic: license-file
